git_dumper.py
git_dumper-1.0.8.dist-info/LICENSE
git_dumper-1.0.8.dist-info/METADATA
git_dumper-1.0.8.dist-info/WHEEL
git_dumper-1.0.8.dist-info/entry_points.txt
git_dumper-1.0.8.dist-info/top_level.txt
git_dumper-1.0.8.dist-info/RECORD
