Metadata-Version: 2.1
Name: git-dumper
Version: 1.0.8
Summary: A tool to dump a git repository from a website
Home-page: https://github.com/arthaud/git-dumper
Author: Maxime Arthaud
Author-email: maxime@arthaud.me
License: MIT
Keywords: dump,git,repository,security,vulnerability,ctf
Classifier: Development Status :: 5 - Production/Stable
Classifier: License :: OSI Approved :: MIT License
Classifier: Topic :: Security
Requires-Python: >=3.0
License-File: LICENSE
Requires-Dist: PySocks
Requires-Dist: requests
Requires-Dist: beautifulsoup4
Requires-Dist: dulwich
Requires-Dist: requests-pkcs12
